huggyva.py
huggyva-0.1.0.dist-info/LICENSE
huggyva-0.1.0.dist-info/METADATA
huggyva-0.1.0.dist-info/WHEEL
huggyva-0.1.0.dist-info/RECORD
