Metadata-Version: 2.3
Name: huggyva
Version: 0.1.0
Summary: Huggingface Seq2SeqML models based voice assistant/chat!
Author: AshkanFeyzollahi
Author-email: ashkanfeyzollahi@gmail.com
Requires-Python: >=3.11
Classifier: Programming Language :: Python :: 3
Classifier: Programming Language :: Python :: 3.11
Classifier: Programming Language :: Python :: 3.12
Classifier: Programming Language :: Python :: 3.13
Requires-Dist: pyttsx3 (>=2.98,<3.0)
Requires-Dist: rich (>=14.0.0,<15.0.0)
Requires-Dist: speechrecognition (>=3.14.2,<4.0.0)
Requires-Dist: torch (>=2.6.0,<3.0.0)
Requires-Dist: transformers (>=4.51.2,<5.0.0)
